<?xml version="1.0" encoding="windows-1252" ?>
<!DOCTYPE ViewObject SYSTEM "jbo_03_01.dtd">
<!---->
<ViewObject
  xmlns="http://xmlns.oracle.com/bc4j"
  Name="DssReinstatementRequestFormView"
  Version="12.2.1.0.31"
  InheritPersonalization="merge"
  BindingStyle="OracleName"
  CustomQuery="true"
  PageIterMode="Full"
  ComponentClass="pqt.dss.rrf.model.vo.DssReinstatementRequestFormViewImpl"
  ComponentInterface="pqt.dss.rrf.model.vo.common.DssReinstatementRequestFormView"
  ClientProxyName="pqt.dss.rrf.model.vo.client.DssReinstatementRequestFormViewClient">
  <DesignTime>
    <Attr Name="_isExpertMode" Value="true"/>
    <Attr Name="_codeGenFlag2" Value="Coll|VarAccess"/>
  </DesignTime>
  <Variable
    Name="VC_Manager_Agent_Name"
    Kind="viewcriteria"
    Type="java.lang.String">
    <Properties>
      <SchemaBasedProperties>
        <LABEL
          ResId="pqt.dss.rrf.model.vo.DssReinstatementRequestFormView.VC_Manager_Agent_Name_LABEL"/>
        <DISPLAYWIDTH
          Value="60"/>
      </SchemaBasedProperties>
    </Properties>
  </Variable>
  <Variable
    Name="VC_ACCOUNT_NO"
    Kind="viewcriteria"
    Type="java.lang.String">
    <Properties>
      <SchemaBasedProperties>
        <LABEL
          ResId="pqt.dss.rrf.model.vo.DssReinstatementRequestFormView.VC_ACCOUNT_NO_LABEL"/>
        <DISPLAYWIDTH
          Value="60"/>
      </SchemaBasedProperties>
    </Properties>
  </Variable>
  <Variable
    Name="NVC_WfDocumentId"
    Kind="viewcriteria"
    Type="oracle.jbo.domain.Number">
    <Properties>
      <SchemaBasedProperties>
        <LABEL
          ResId="pqt.dss.rrf.model.vo.DssReinstatementRequestFormView.NVC_WfDocumentId_LABEL"/>
        <DISPLAYWIDTH
          Value="50"/>
      </SchemaBasedProperties>
    </Properties>
  </Variable>
  <Variable
    Name="VC_Doc_No"
    Kind="viewcriteria"
    Type="java.lang.String"/>
  <ViewAccessor
    Name="AgentRankLovVO1"
    ViewObjectName="pqt.dss.rrf.model.lov.AgentRankLovVO"
    RowLevelBinds="true"/>
  <ViewAccessor
    Name="TerminatedAntVO1"
    ViewObjectName="pqt.dss.rrf.model.lov.TerminatedAntVO"
    RowLevelBinds="true">
    <ViewCriteriaUsage
      Name="TerminatedAntVOCriteria"
      FullName="pqt.dss.rrf.model.lov.TerminatedAntVO.TerminatedAntVOCriteria"/>
    <ParameterMap>
      <PIMap Variable="VC_Branch_Code">
        <TransientExpression
          trustMode="untrusted"
          Name="ExpressionScript"><![CDATA[CurrBranchCodeFk]]></TransientExpression>
      </PIMap>
    </ParameterMap>
  </ViewAccessor>
  <ViewAccessor
    Name="BranchDetailLovVO2"
    ViewObjectName="pqt.dss.rrf.model.lov.BranchDetailLovVO"
    RowLevelBinds="true">
    <ViewCriteriaUsage
      Name="CurrentBranchViewCriteria"
      FullName="pqt.dss.rrf.model.lov.BranchDetailLovVO.CurrentBranchViewCriteria"/>
    <ParameterMap>
      <PIMap Variable="VC_UserIdFk">
        <TransientExpression
          trustMode="untrusted"
          Name="ExpressionScript"><![CDATA[UserIdFk]]></TransientExpression>
      </PIMap>
    </ParameterMap>
  </ViewAccessor>
  <ViewAccessor
    Name="NewBranchDtlLov1"
    ViewObjectName="pqt.dss.rrf.model.lov.NewBranchDtlLov"
    RowLevelBinds="true"/>
  <ViewAccessor
    Name="AgentDtlLovVo1"
    ViewObjectName="pqt.dss.rrf.model.lov.AgentDtlLovVo"
    RowLevelBinds="true"/>
  <ListBinding
    Name="LOV_DesignationAppliedFor"
    ListVOName="AgentRankLovVO1"
    ListRangeSize="-1"
    ComboRowCountHint="10"
    NullValueFlag="none"
    MRUCount="0">
    <AttrArray Name="AttrNames">
      <Item Value="DesignationAppliedFor"/>
    </AttrArray>
    <AttrArray Name="AttrExpressions"/>
    <AttrArray Name="DerivedAttrNames">
      <Item Value="NewRankCodeFk"/>
      <Item Value="Nlevel"/>
    </AttrArray>
    <AttrArray Name="ListAttrNames">
      <Item Value="VDescription"/>
      <Item Value="VRankCode"/>
      <Item Value="NLevel"/>
    </AttrArray>
    <AttrArray Name="ListDisplayAttrNames">
      <Item Value="VDescription"/>
    </AttrArray>
    <DisplayCriteria
      Name="AgentRankLovVOCriteria"/>
  </ListBinding>
  <ListBinding
    Name="LOV_AgentCode"
    ListVOName="TerminatedAntVO1"
    ListRangeSize="-1"
    NullValueFlag="start"
    NullValueId="${adfBundle['oracle.javatools.resourcebundle.SystemBundle']['NULL_VALUE_RESID']}"
    MRUCount="0">
    <AttrArray Name="AttrNames">
      <Item Value="AgentCode"/>
    </AttrArray>
    <AttrArray Name="AttrExpressions"/>
    <AttrArray Name="DerivedAttrNames">
      <Item Value="AgentName"/>
      <Item Value="BankAccNo"/>
      <Item Value="CurrentDesignation"/>
      <Item Value="Status"/>
      <Item Value="StartDate"/>
      <Item Value="EndDate"/>
      <Item Value="AgentNoFk"/>
      <Item Value="QuarterBuss"/>
      <Item Value="QuarterBussPol"/>
      <Item Value="HalfyearBuss"/>
      <Item Value="HalfyearBussPol"/>
      <Item Value="YearlyBuss"/>
      <Item Value="YearlyBussPol"/>
      <Item Value="TerminationDate"/>
      <Item Value="NoOfResignation"/>
      <Item Value="NoOfTermination"/>
    </AttrArray>
    <AttrArray Name="ListAttrNames">
      <Item Value="VAgentCode"/>
      <Item Value="AgentName"/>
      <Item Value="VCommBankAcctNo"/>
      <Item Value="AgentRank"/>
      <Item Value="VStatus"/>
      <Item Value="DStartDate"/>
      <Item Value="DEndDate"/>
      <Item Value="NAgentNo"/>
      <Item Value="NCqBus"/>
      <Item Value="NCqBusPol"/>
      <Item Value="NHyBus"/>
      <Item Value="NHyBusPol"/>
      <Item Value="NYrBus"/>
      <Item Value="NYrBusPol"/>
      <Item Value="DTermination"/>
      <Item Value="NoActionResignation"/>
      <Item Value="NoActionTermination"/>
    </AttrArray>
    <AttrArray Name="ListDisplayAttrNames">
      <Item Value="AgentName"/>
      <Item Value="VAgentCode"/>
      <Item Value="MgrAgentName"/>
      <Item Value="AgentRank"/>
    </AttrArray>
    <DisplayCriteria
      Name="TerminatedAntVOCriteria"/>
  </ListBinding>
  <ListBinding
    Name="UsertBranchDtlLOV"
    ListVOName="BranchDetailLovVO2"
    ListRangeSize="-1"
    NullValueFlag="start"
    NullValueId="${adfBundle['oracle.javatools.resourcebundle.SystemBundle']['NULL_VALUE_RESID']}"
    MRUCount="0">
    <AttrArray Name="AttrNames">
      <Item Value="CurrentBranch"/>
    </AttrArray>
    <AttrArray Name="AttrExpressions"/>
    <AttrArray Name="DerivedAttrNames">
      <Item Value="CurrBranchCodeFk"/>
    </AttrArray>
    <AttrArray Name="ListAttrNames">
      <Item Value="VBranchName"/>
      <Item Value="VBranchCode"/>
    </AttrArray>
    <DisplayCriteria/>
  </ListBinding>
  <ListBinding
    Name="LOV_NewBranch"
    ListVOName="NewBranchDtlLov1"
    ListRangeSize="-1"
    NullValueFlag="none"
    MRUCount="0"
    ComboRowCountHint="10">
    <AttrArray Name="AttrNames">
      <Item Value="NewBranch"/>
    </AttrArray>
    <AttrArray Name="AttrExpressions"/>
    <AttrArray Name="DerivedAttrNames">
      <Item Value="NewBranchCodeFk"/>
    </AttrArray>
    <AttrArray Name="ListAttrNames">
      <Item Value="VBranchName"/>
      <Item Value="VBranchCode"/>
    </AttrArray>
    <AttrArray Name="ListDisplayAttrNames">
      <Item Value="VBranchCode"/>
      <Item Value="VBranchName"/>
    </AttrArray>
    <DisplayCriteria
      Name="NewBranchDtlLovCriteria"/>
  </ListBinding>
  <ListBinding
    Name="LOV_MgrCode"
    ListVOName="AgentDtlLovVo1"
    ListRangeSize="-1"
    ComboRowCountHint="10"
    NullValueFlag="none"
    MRUCount="0">
    <AttrArray Name="AttrNames">
      <Item Value="MgrCode"/>
    </AttrArray>
    <AttrArray Name="AttrExpressions"/>
    <AttrArray Name="DerivedAttrNames">
      <Item Value="MgrName"/>
      <Item Value="ReportingManagerNoFk"/>
    </AttrArray>
    <AttrArray Name="ListAttrNames">
      <Item Value="MgrAgentCode"/>
      <Item Value="MgrAgentName"/>
      <Item Value="MgrNAgentNo"/>
    </AttrArray>
    <AttrArray Name="ListDisplayAttrNames">
      <Item Value="MgrAgentCode"/>
      <Item Value="MgrAgentName"/>
      <Item Value="MgrRankCode"/>
    </AttrArray>
    <DisplayCriteria
      Name="AgentDtlLovVoCriteria"/>
  </ListBinding>
  <SQLQuery><![CDATA[SELECT DSSREINSTATEMENTREQUESTFORM.AGENT_NO_FK,                     
       DSSREINSTATEMENTREQUESTFORM.BANK_ACC_NO,                     
       DSSREINSTATEMENTREQUESTFORM.CURRENT_RANK_CODE_FK,                     
       DSSREINSTATEMENTREQUESTFORM.EFFECTIVE_FROM,                     
       DSSREINSTATEMENTREQUESTFORM.END_DATE,                     
       DSSREINSTATEMENTREQUESTFORM.ENTER_DATE,                     
       DSSREINSTATEMENTREQUESTFORM.LAST_UPDATED_BY,                     
       DSSREINSTATEMENTREQUESTFORM.LAST_UPDATED_DATE,                     
       DSSREINSTATEMENTREQUESTFORM.NEW_RANK_CODE_FK,                     
       DSSREINSTATEMENTREQUESTFORM.REMARKS,                     
       DSSREINSTATEMENTREQUESTFORM.REPORTING_MANAGER_NO_FK,                     
       DSSREINSTATEMENTREQUESTFORM.RRF_ID_PK,                     
       DSSREINSTATEMENTREQUESTFORM.START_DATE,                     
       DSSREINSTATEMENTREQUESTFORM.STATUS,                     
       DSSREINSTATEMENTREQUESTFORM.UL_NO,                     
       DSSREINSTATEMENTREQUESTFORM.USER_ID_FK,                     
       DSSREINSTATEMENTREQUESTFORM.DSS_STATUS,                     
       DSSREINSTATEMENTREQUESTFORM.BRANCH_STATUS,                     
       DSSREINSTATEMENTREQUESTFORM.DSS_NOTIF_ID_FK,                     
       DSSREINSTATEMENTREQUESTFORM.BRANCH_NOTIF_ID_FK,                     
       DSSREINSTATEMENTREQUESTFORM.Curr_Branch_Code_Fk,                     
       DSSREINSTATEMENTREQUESTFORM.New_Branch_Code_Fk,              
       DSSREINSTATEMENTREQUESTFORM.Rrf_Doc_No, 
       DSSREINSTATEMENTREQUESTFORM.WORKFLOW_STATUS, 
       DSSREINSTATEMENTREQUESTFORM.WORKFLOW_NOTIFICATION_ID,              
       (SELECT AG.V_AGENT_CODE                     
          FROM DSS_TERMINATED_AGENT_VIEW AG                     
         WHERE AG.N_AGENT_NO = DSSREINSTATEMENTREQUESTFORM.AGENT_NO_FK) AGENT_CODE,                     
       (SELECT AG.AGENT_NAME                     
          FROM DSS_TERMINATED_AGENT_VIEW AG                     
         WHERE AG.N_AGENT_NO = DSSREINSTATEMENTREQUESTFORM.AGENT_NO_FK) AGENT_NAME,            
         (SELECT AG.N_POLICIES                    
          FROM DSS_TERMINATED_AGENT_VIEW AG                    
         WHERE AG.N_AGENT_NO = DSSREINSTATEMENTREQUESTFORM.AGENT_NO_FK) BusPolicy,            
         (SELECT AG.N_ISS_CON                    
          FROM DSS_TERMINATED_AGENT_VIEW AG                    
         WHERE AG.N_AGENT_NO = DSSREINSTATEMENTREQUESTFORM.AGENT_NO_FK) BusIssueCont,            
         (SELECT AG.N_ISS_TOP                    
          FROM DSS_TERMINATED_AGENT_VIEW AG                    
         WHERE AG.N_AGENT_NO = DSSREINSTATEMENTREQUESTFORM.AGENT_NO_FK) BusIssueTop,          
         (SELECT AG.TOTAL_CONT                   
          FROM DSS_TERMINATED_AGENT_VIEW AG                    
         WHERE AG.N_AGENT_NO = DSSREINSTATEMENTREQUESTFORM.AGENT_NO_FK) TOTAL_CONT,        
         (SELECT ag.n_cq_bus_pol                               
          FROM DSS_TERMINATED_AGENT_VIEW AG                                
         WHERE Ag.N_AGENT_NO = DSSREINSTATEMENTREQUESTFORM.Agent_No_Fk) Quarter_buss_pol,          
         (SELECT ag.n_cq_bus                               
          FROM DSS_TERMINATED_AGENT_VIEW AG                                
         WHERE Ag.N_AGENT_NO = DSSREINSTATEMENTREQUESTFORM.Agent_No_Fk) Quarter_buss,          
         (SELECT ag.n_hy_bus_pol                               
          FROM DSS_TERMINATED_AGENT_VIEW AG                                
         WHERE Ag.N_AGENT_NO = DSSREINSTATEMENTREQUESTFORM.Agent_No_Fk) HalfYear_buss_pol,          
          (SELECT ag.n_hy_bus                               
          FROM DSS_TERMINATED_AGENT_VIEW AG                                
         WHERE Ag.N_AGENT_NO = DSSREINSTATEMENTREQUESTFORM.Agent_No_Fk) HalfYear_buss,          
         (SELECT ag.n_yr_bus_pol                               
          FROM DSS_TERMINATED_AGENT_VIEW AG                                
         WHERE Ag.N_AGENT_NO = DSSREINSTATEMENTREQUESTFORM.Agent_No_Fk) Yearly_buss_pol,          
         (SELECT ag.n_yr_bus                               
          FROM DSS_TERMINATED_AGENT_VIEW AG                                
         WHERE Ag.N_AGENT_NO = DSSREINSTATEMENTREQUESTFORM.Agent_No_Fk) Yearly_buss,        
         (SELECT AG.TRANDATE                    
          FROM DSS_TERMINATED_AGENT_VIEW AG                    
         WHERE AG.N_AGENT_NO = DSSREINSTATEMENTREQUESTFORM.AGENT_NO_FK) BusDate,            
       (SELECT AR.V_DESCRIPTION                     
          FROM DSS_AGENT_RANK_VIEW AR                     
         WHERE AR.V_RANK_CODE = DSSREINSTATEMENTREQUESTFORM.NEW_RANK_CODE_FK) DESIGNATION_APPLIED_FOR,       
         (SELECT AG.D_TERMINATION       
          FROM DSS_TERMINATED_AGENT_VIEW AG       
         WHERE AG.N_AGENT_NO = DSSREINSTATEMENTREQUESTFORM.AGENT_NO_FK) TERMINATION_DATE,       
       (SELECT AG.MGR_N_AGENT_NO                     
          FROM DSS_TERMINATED_AGENT_VIEW AG                     
         WHERE AG.N_AGENT_NO = DSSREINSTATEMENTREQUESTFORM.AGENT_NO_FK) MGR_N_AGENT_NO,                     
       (SELECT AG.MGR_AGENT_CODE                     
          FROM DSS_TERMINATED_AGENT_VIEW AG                     
         WHERE AG.N_AGENT_NO = DSSREINSTATEMENTREQUESTFORM.AGENT_NO_FK) MGR_AGENT_CODE,                     
       (SELECT AG.MGR_AGENT_NAME                     
          FROM DSS_TERMINATED_AGENT_VIEW AG                     
         WHERE AG.N_AGENT_NO = DSSREINSTATEMENTREQUESTFORM.AGENT_NO_FK) MGR_AGENT_NAME,       
          (SELECT DISTINCT MG.MGR_N_AGENT_NO                    
          FROM VU_DSS_RRF_AGENT_VIEW MG                    
         WHERE MG.MGR_N_AGENT_NO = DSSREINSTATEMENTREQUESTFORM.REPORTING_MANAGER_NO_FK) MGR_N_NO,      
        (SELECT DISTINCT MG.MGR_AGENT_NAME                    
          FROM VU_DSS_RRF_AGENT_VIEW MG                   
         WHERE MG.MGR_N_AGENT_NO = DSSREINSTATEMENTREQUESTFORM.REPORTING_MANAGER_NO_FK) MGR_NAME,     
         (SELECT DISTINCT MG.MGR_AGENT_CODE                    
          FROM VU_DSS_RRF_AGENT_VIEW MG                    
         WHERE MG.MGR_N_AGENT_NO = DSSREINSTATEMENTREQUESTFORM.REPORTING_MANAGER_NO_FK) MGR_CODE,     
       (SELECT AG.AGENT_RANK                     
          FROM DSS_TERMINATED_AGENT_VIEW AG                     
         WHERE AG.N_AGENT_NO = DSSREINSTATEMENTREQUESTFORM.AGENT_NO_FK) CURRENT_DESIGNATION,                     
       (SELECT AR.N_LEVEL                     
          FROM DSS_AGENT_RANK_VIEW AR                     
         WHERE AR.V_RANK_CODE = DSSREINSTATEMENTREQUESTFORM.NEW_RANK_CODE_FK) NLEVEL,                   
         (SELECT AG.V_BRANCH_NAME                              
          FROM DSS_TERMINATED_AGENT_VIEW AG                             
         WHERE AG.N_AGENT_NO = DSSREINSTATEMENTREQUESTFORM.AGENT_NO_FK) CURRENT_BRANCH,                              
       (SELECT TBR.V_BRANCH_NAME                              
          FROM VU_DSS_ST_BRANCH TBR                              
         WHERE TBR.V_BRANCH_CODE = DSSREINSTATEMENTREQUESTFORM.New_Branch_Code_Fk) NEW_BRANCH,         
       (SELECT TBR.V_BRANCH_NAME         
          FROM VU_DSS_ST_BRANCH TBR         
         WHERE TBR.V_BRANCH_CODE =         
               DSSREINSTATEMENTREQUESTFORM.CURR_BRANCH_CODE_FK) USER_BRANCH,  
       (SELECT AG.NO_ACTION_TERMINATION  
          FROM DSS_TERMINATED_AGENT_VIEW AG  
         WHERE AG.N_AGENT_NO = DSSREINSTATEMENTREQUESTFORM.AGENT_NO_FK) NO_OF_TERMINATION,  
       (SELECT AG.NO_ACTION_RESIGNATION  
          FROM DSS_TERMINATED_AGENT_VIEW AG  
         WHERE AG.N_AGENT_NO = DSSREINSTATEMENTREQUESTFORM.AGENT_NO_FK) NO_OF_RESIGNATION                     
  FROM DSS_REINSTATEMENT_REQUEST_FORM DSSREINSTATEMENTREQUESTFORM]]></SQLQuery>
  <EntityUsage
    Name="DssReinstatementRequestForm"
    Entity="pqt.dss.rrf.model.eo.DssReinstatementRequestForm"/>
  <ViewAttribute
    Name="AgentNoFk"
    PrecisionRule="true"
    EntityAttrName="AgentNoFk"
    EntityUsage="DssReinstatementRequestForm"
    AliasName="AGENT_NO_FK"/>
  <ViewAttribute
    Name="BankAccNo"
    PrecisionRule="true"
    EntityAttrName="BankAccNo"
    EntityUsage="DssReinstatementRequestForm"
    AliasName="BANK_ACC_NO"/>
  <ViewAttribute
    Name="CurrentRankCodeFk"
    PrecisionRule="true"
    EntityAttrName="CurrentRankCodeFk"
    EntityUsage="DssReinstatementRequestForm"
    AliasName="CURRENT_RANK_CODE_FK"/>
  <ViewAttribute
    Name="EffectiveFrom"
    PrecisionRule="true"
    EntityAttrName="EffectiveFrom"
    EntityUsage="DssReinstatementRequestForm"
    AliasName="EFFECTIVE_FROM">
    <Properties>
      <SchemaBasedProperties>
        <FMT_FORMATTER
          ResId="pqt.dss.rrf.model.vo.DssReinstatementRequestFormView.EffectiveFrom_FMT_FORMATTER"/>
        <FMT_FORMAT
          ResId="pqt.dss.rrf.model.vo.DssReinstatementRequestFormView.EffectiveFrom_FMT_FORMAT"/>
      </SchemaBasedProperties>
    </Properties>
  </ViewAttribute>
  <ViewAttribute
    Name="EndDate"
    PrecisionRule="true"
    EntityAttrName="EndDate"
    EntityUsage="DssReinstatementRequestForm"
    AliasName="END_DATE">
    <Properties>
      <SchemaBasedProperties>
        <FMT_FORMATTER
          ResId="pqt.dss.rrf.model.vo.DssReinstatementRequestFormView.EndDate_FMT_FORMATTER"/>
        <LABEL
          ResId="pqt.dss.rrf.model.vo.DssReinstatementRequestFormView.EndDate_LABEL"/>
        <FMT_FORMAT
          ResId="pqt.dss.rrf.model.vo.DssReinstatementRequestFormView.EndDate_FMT_FORMAT"/>
      </SchemaBasedProperties>
    </Properties>
  </ViewAttribute>
  <ViewAttribute
    Name="EnterDate"
    PrecisionRule="true"
    EntityAttrName="EnterDate"
    EntityUsage="DssReinstatementRequestForm"
    AliasName="ENTER_DATE"/>
  <ViewAttribute
    Name="LastUpdatedBy"
    PrecisionRule="true"
    EntityAttrName="LastUpdatedBy"
    EntityUsage="DssReinstatementRequestForm"
    AliasName="LAST_UPDATED_BY"/>
  <ViewAttribute
    Name="LastUpdatedDate"
    PrecisionRule="true"
    EntityAttrName="LastUpdatedDate"
    EntityUsage="DssReinstatementRequestForm"
    AliasName="LAST_UPDATED_DATE"/>
  <ViewAttribute
    Name="NewRankCodeFk"
    PrecisionRule="true"
    EntityAttrName="NewRankCodeFk"
    EntityUsage="DssReinstatementRequestForm"
    AliasName="NEW_RANK_CODE_FK"/>
  <ViewAttribute
    Name="Remarks"
    PrecisionRule="true"
    EntityAttrName="Remarks"
    EntityUsage="DssReinstatementRequestForm"
    AliasName="REMARKS">
    <Properties>
      <SchemaBasedProperties>
        <DISPLAYWIDTH
          Value="50"/>
      </SchemaBasedProperties>
    </Properties>
  </ViewAttribute>
  <ViewAttribute
    Name="ReportingManagerNoFk"
    PrecisionRule="true"
    EntityAttrName="ReportingManagerNoFk"
    EntityUsage="DssReinstatementRequestForm"
    AliasName="REPORTING_MANAGER_NO_FK"/>
  <ViewAttribute
    Name="RrfIdPk"
    IsNotNull="true"
    PrecisionRule="true"
    EntityAttrName="RrfIdPk"
    EntityUsage="DssReinstatementRequestForm"
    AliasName="RRF_ID_PK"/>
  <ViewAttribute
    Name="StartDate"
    PrecisionRule="true"
    EntityAttrName="StartDate"
    EntityUsage="DssReinstatementRequestForm"
    AliasName="START_DATE">
    <Properties>
      <SchemaBasedProperties>
        <FMT_FORMAT
          ResId="pqt.dss.rrf.model.vo.DssReinstatementRequestFormView.StartDate_FMT_FORMAT"/>
        <FMT_FORMATTER
          ResId="pqt.dss.rrf.model.vo.DssReinstatementRequestFormView.StartDate_FMT_FORMATTER"/>
      </SchemaBasedProperties>
    </Properties>
  </ViewAttribute>
  <ViewAttribute
    Name="Status"
    PrecisionRule="true"
    EntityAttrName="Status"
    EntityUsage="DssReinstatementRequestForm"
    AliasName="STATUS"/>
  <ViewAttribute
    Name="UlNo"
    PrecisionRule="true"
    EntityAttrName="UlNo"
    EntityUsage="DssReinstatementRequestForm"
    AliasName="UL_NO"/>
  <ViewAttribute
    Name="UserIdFk"
    PrecisionRule="true"
    EntityAttrName="UserIdFk"
    EntityUsage="DssReinstatementRequestForm"
    AliasName="USER_ID_FK"/>
  <ViewAttribute
    Name="DssStatus"
    PrecisionRule="true"
    EntityAttrName="DssStatus"
    EntityUsage="DssReinstatementRequestForm"
    AliasName="DSS_STATUS"/>
  <ViewAttribute
    Name="BranchStatus"
    PrecisionRule="true"
    EntityAttrName="BranchStatus"
    EntityUsage="DssReinstatementRequestForm"
    AliasName="BRANCH_STATUS"/>
  <ViewAttribute
    Name="DssNotifIdFk"
    PrecisionRule="true"
    EntityAttrName="DssNotifIdFk"
    EntityUsage="DssReinstatementRequestForm"
    AliasName="DSS_NOTIF_ID_FK"/>
  <ViewAttribute
    Name="BranchNotifIdFk"
    PrecisionRule="true"
    EntityAttrName="BranchNotifIdFk"
    EntityUsage="DssReinstatementRequestForm"
    AliasName="BRANCH_NOTIF_ID_FK"/>
  <ViewAttribute
    Name="CurrBranchCodeFk"
    PrecisionRule="true"
    EntityAttrName="CurrBranchCodeFk"
    EntityUsage="DssReinstatementRequestForm"
    AliasName="CURR_BRANCH_CODE_FK"/>
  <ViewAttribute
    Name="NewBranchCodeFk"
    PrecisionRule="true"
    EntityAttrName="NewBranchCodeFk"
    EntityUsage="DssReinstatementRequestForm"
    AliasName="NEW_BRANCH_CODE_FK"/>
  <ViewAttribute
    Name="RrfDocNo"
    PrecisionRule="true"
    EntityAttrName="RrfDocNo"
    EntityUsage="DssReinstatementRequestForm"
    AliasName="RRF_DOC_NO">
    <Properties>
      <SchemaBasedProperties>
        <LABEL
          ResId="pqt.dss.rrf.model.vo.DssReinstatementRequestFormView.RrfDocNo_LABEL"/>
        <DISPLAYWIDTH
          Value="50"/>
      </SchemaBasedProperties>
    </Properties>
  </ViewAttribute>
  <ViewAttribute
    Name="WorkflowStatus"
    PrecisionRule="true"
    EntityAttrName="WorkflowStatus"
    EntityUsage="DssReinstatementRequestForm"
    AliasName="WORKFLOW_STATUS">
    <Properties>
      <SchemaBasedProperties>
        <LABEL
          ResId="pqt.dss.rrf.model.vo.DssReinstatementRequestFormView.WorkflowStatus_LABEL"/>
      </SchemaBasedProperties>
    </Properties>
  </ViewAttribute>
  <ViewAttribute
    Name="WorkflowNotificationId"
    PrecisionRule="true"
    EntityAttrName="WorkflowNotificationId"
    EntityUsage="DssReinstatementRequestForm"
    AliasName="WORKFLOW_NOTIFICATION_ID"/>
  <ViewAttribute
    Name="AgentCode"
    IsPersistent="false"
    PrecisionRule="true"
    Precision="30"
    Type="java.lang.String"
    ColumnType="VARCHAR2"
    AliasName="AGENT_CODE"
    Expression="AGENT_CODE"
    SQLType="VARCHAR"
    LOVName="LOV_AgentCode"
    IsNotNull="true">
    <DesignTime>
      <Attr Name="_DisplaySize" Value="30"/>
    </DesignTime>
    <Properties>
      <SchemaBasedProperties>
        <LABEL
          ResId="pqt.dss.rrf.model.vo.DssReinstatementRequestFormView.AgentCode_LABEL"/>
        <DISPLAYWIDTH
          Value="50"/>
        <CONTROLTYPE
          Value="input_text_lov"/>
      </SchemaBasedProperties>
    </Properties>
  </ViewAttribute>
  <ViewAttribute
    Name="AgentName"
    IsPersistent="false"
    PrecisionRule="true"
    Precision="4000"
    Type="java.lang.String"
    ColumnType="VARCHAR2"
    AliasName="AGENT_NAME"
    Expression="AGENT_NAME"
    SQLType="VARCHAR">
    <DesignTime>
      <Attr Name="_DisplaySize" Value="4000"/>
    </DesignTime>
    <Properties>
      <SchemaBasedProperties>
        <LABEL
          ResId="pqt.dss.rrf.model.vo.DssReinstatementRequestFormView.AgentName_LABEL"/>
        <DISPLAYWIDTH
          Value="50"/>
      </SchemaBasedProperties>
    </Properties>
  </ViewAttribute>
  <ViewAttribute
    Name="Buspolicy"
    IsPersistent="false"
    PrecisionRule="true"
    Type="oracle.jbo.domain.Number"
    ColumnType="NUMBER"
    AliasName="BUSPOLICY"
    Expression="BUSPOLICY"
    SQLType="NUMERIC">
    <Properties>
      <SchemaBasedProperties>
        <LABEL
          ResId="pqt.dss.rrf.model.vo.DssReinstatementRequestFormView.Buspolicy_LABEL"/>
        <DISPLAYWIDTH
          Value="50"/>
      </SchemaBasedProperties>
    </Properties>
  </ViewAttribute>
  <ViewAttribute
    Name="Busissuecont"
    IsPersistent="false"
    PrecisionRule="true"
    Type="oracle.jbo.domain.Number"
    ColumnType="NUMBER"
    AliasName="BUSISSUECONT"
    Expression="BUSISSUECONT"
    SQLType="NUMERIC">
    <Properties>
      <SchemaBasedProperties>
        <DISPLAYWIDTH
          Value="50"/>
        <LABEL
          ResId="pqt.dss.rrf.model.vo.DssReinstatementRequestFormView.Busissuecont_LABEL"/>
        <FMT_FORMATTER
          ResId="pqt.dss.rrf.model.vo.DssReinstatementRequestFormView.Busissuecont_FMT_FORMATTER"/>
        <FMT_FORMAT
          ResId="pqt.dss.rrf.model.vo.DssReinstatementRequestFormView.Busissuecont_FMT_FORMAT"/>
      </SchemaBasedProperties>
    </Properties>
  </ViewAttribute>
  <ViewAttribute
    Name="Busissuetop"
    IsPersistent="false"
    PrecisionRule="true"
    Type="oracle.jbo.domain.Number"
    ColumnType="NUMBER"
    AliasName="BUSISSUETOP"
    Expression="BUSISSUETOP"
    SQLType="NUMERIC">
    <Properties>
      <SchemaBasedProperties>
        <DISPLAYWIDTH
          Value="50"/>
        <LABEL
          ResId="pqt.dss.rrf.model.vo.DssReinstatementRequestFormView.Busissuetop_LABEL"/>
        <FMT_FORMATTER
          ResId="pqt.dss.rrf.model.vo.DssReinstatementRequestFormView.Busissuetop_FMT_FORMATTER"/>
        <FMT_FORMAT
          ResId="pqt.dss.rrf.model.vo.DssReinstatementRequestFormView.Busissuetop_FMT_FORMAT"/>
      </SchemaBasedProperties>
    </Properties>
  </ViewAttribute>
  <ViewAttribute
    Name="TotalCont"
    IsPersistent="false"
    PrecisionRule="true"
    Type="oracle.jbo.domain.Number"
    ColumnType="NUMBER"
    AliasName="TOTAL_CONT"
    Expression="TOTAL_CONT"
    SQLType="NUMERIC">
    <Properties>
      <SchemaBasedProperties>
        <LABEL
          ResId="pqt.dss.rrf.model.vo.DssReinstatementRequestFormView.TotalCont_LABEL"/>
        <FMT_FORMATTER
          ResId="pqt.dss.rrf.model.vo.DssReinstatementRequestFormView.TotalCont_FMT_FORMATTER"/>
        <FMT_FORMAT
          ResId="pqt.dss.rrf.model.vo.DssReinstatementRequestFormView.TotalCont_FMT_FORMAT"/>
      </SchemaBasedProperties>
    </Properties>
  </ViewAttribute>
  <ViewAttribute
    Name="QuarterBussPol"
    IsPersistent="false"
    PrecisionRule="true"
    Type="oracle.jbo.domain.Number"
    ColumnType="NUMBER"
    AliasName="QUARTER_BUSS_POL"
    Expression="QUARTER_BUSS_POL"
    SQLType="NUMERIC">
    <Properties>
      <SchemaBasedProperties>
        <LABEL
          ResId="pqt.dss.rrf.model.vo.DssReinstatementRequestFormView.QuarterBussPol_LABEL"/>
      </SchemaBasedProperties>
    </Properties>
  </ViewAttribute>
  <ViewAttribute
    Name="QuarterBuss"
    IsPersistent="false"
    PrecisionRule="true"
    Type="oracle.jbo.domain.Number"
    ColumnType="NUMBER"
    AliasName="QUARTER_BUSS"
    Expression="QUARTER_BUSS"
    SQLType="NUMERIC">
    <Properties>
      <SchemaBasedProperties>
        <LABEL
          ResId="pqt.dss.rrf.model.vo.DssReinstatementRequestFormView.QuarterBuss_LABEL"/>
      </SchemaBasedProperties>
    </Properties>
  </ViewAttribute>
  <ViewAttribute
    Name="HalfyearBussPol"
    IsPersistent="false"
    PrecisionRule="true"
    Type="oracle.jbo.domain.Number"
    ColumnType="NUMBER"
    AliasName="HALFYEAR_BUSS_POL"
    Expression="HALFYEAR_BUSS_POL"
    SQLType="NUMERIC">
    <Properties>
      <SchemaBasedProperties>
        <LABEL
          ResId="pqt.dss.rrf.model.vo.DssReinstatementRequestFormView.HalfyearBussPol_LABEL"/>
      </SchemaBasedProperties>
    </Properties>
  </ViewAttribute>
  <ViewAttribute
    Name="HalfyearBuss"
    IsPersistent="false"
    PrecisionRule="true"
    Type="oracle.jbo.domain.Number"
    ColumnType="NUMBER"
    AliasName="HALFYEAR_BUSS"
    Expression="HALFYEAR_BUSS"
    SQLType="NUMERIC">
    <Properties>
      <SchemaBasedProperties>
        <LABEL
          ResId="pqt.dss.rrf.model.vo.DssReinstatementRequestFormView.HalfyearBuss_LABEL"/>
      </SchemaBasedProperties>
    </Properties>
  </ViewAttribute>
  <ViewAttribute
    Name="YearlyBussPol"
    IsPersistent="false"
    PrecisionRule="true"
    Type="oracle.jbo.domain.Number"
    ColumnType="NUMBER"
    AliasName="YEARLY_BUSS_POL"
    Expression="YEARLY_BUSS_POL"
    SQLType="NUMERIC">
    <Properties>
      <SchemaBasedProperties>
        <LABEL
          ResId="pqt.dss.rrf.model.vo.DssReinstatementRequestFormView.YearlyBussPol_LABEL"/>
      </SchemaBasedProperties>
    </Properties>
  </ViewAttribute>
  <ViewAttribute
    Name="YearlyBuss"
    IsPersistent="false"
    PrecisionRule="true"
    Type="oracle.jbo.domain.Number"
    ColumnType="NUMBER"
    AliasName="YEARLY_BUSS"
    Expression="YEARLY_BUSS"
    SQLType="NUMERIC">
    <Properties>
      <SchemaBasedProperties>
        <LABEL
          ResId="pqt.dss.rrf.model.vo.DssReinstatementRequestFormView.YearlyBuss_LABEL"/>
      </SchemaBasedProperties>
    </Properties>
  </ViewAttribute>
  <ViewAttribute
    Name="Busdate"
    IsUpdateable="false"
    IsPersistent="false"
    PrecisionRule="true"
    Type="oracle.jbo.domain.Date"
    ColumnType="DATE"
    AliasName="BUSDATE"
    Expression="BUSDATE"
    SQLType="DATE"/>
  <ViewAttribute
    Name="DesignationAppliedFor"
    IsPersistent="false"
    PrecisionRule="true"
    Precision="100"
    Type="java.lang.String"
    ColumnType="VARCHAR2"
    AliasName="DESIGNATION_APPLIED_FOR"
    Expression="DESIGNATION_APPLIED_FOR"
    SQLType="VARCHAR"
    LOVName="LOV_DesignationAppliedFor"
    IsNotNull="true">
    <DesignTime>
      <Attr Name="_DisplaySize" Value="100"/>
    </DesignTime>
    <Properties>
      <SchemaBasedProperties>
        <LABEL
          ResId="pqt.dss.rrf.model.vo.DssReinstatementRequestFormView.DesignationAppliedFor_LABEL"/>
        <DISPLAYWIDTH
          Value="50"/>
        <CONTROLTYPE
          Value="input_text_lov"/>
      </SchemaBasedProperties>
    </Properties>
  </ViewAttribute>
  <ViewAttribute
    Name="TerminationDate"
    IsPersistent="false"
    PrecisionRule="true"
    Type="oracle.jbo.domain.Date"
    ColumnType="DATE"
    AliasName="TERMINATION_DATE"
    Expression="TERMINATION_DATE"
    SQLType="DATE">
    <Properties>
      <SchemaBasedProperties>
        <LABEL
          ResId="pqt.dss.rrf.model.vo.DssReinstatementRequestFormView.TerminationDate_LABEL"/>
        <FMT_FORMATTER
          ResId="pqt.dss.rrf.model.vo.DssReinstatementRequestFormView.TerminationDate_FMT_FORMATTER"/>
        <FMT_FORMAT
          ResId="pqt.dss.rrf.model.vo.DssReinstatementRequestFormView.TerminationDate_FMT_FORMAT"/>
      </SchemaBasedProperties>
    </Properties>
  </ViewAttribute>
  <ViewAttribute
    Name="MgrNAgentNo"
    IsPersistent="false"
    PrecisionRule="true"
    Type="oracle.jbo.domain.Number"
    ColumnType="NUMBER"
    AliasName="MGR_N_AGENT_NO"
    Expression="MGR_N_AGENT_NO"
    SQLType="NUMERIC"/>
  <ViewAttribute
    Name="MgrAgentCode"
    IsPersistent="false"
    PrecisionRule="true"
    Precision="30"
    Type="java.lang.String"
    ColumnType="VARCHAR2"
    AliasName="MGR_AGENT_CODE"
    Expression="MGR_AGENT_CODE"
    SQLType="VARCHAR"
    IsNotNull="true">
    <DesignTime>
      <Attr Name="_DisplaySize" Value="30"/>
    </DesignTime>
    <Properties>
      <SchemaBasedProperties>
        <LABEL
          ResId="pqt.dss.rrf.model.vo.DssReinstatementRequestFormView.MgrAgentCode_LABEL"/>
      </SchemaBasedProperties>
    </Properties>
  </ViewAttribute>
  <ViewAttribute
    Name="MgrAgentName"
    IsPersistent="false"
    PrecisionRule="true"
    Precision="4000"
    Type="java.lang.String"
    ColumnType="VARCHAR2"
    AliasName="MGR_AGENT_NAME"
    Expression="MGR_AGENT_NAME"
    SQLType="VARCHAR">
    <DesignTime>
      <Attr Name="_DisplaySize" Value="4000"/>
    </DesignTime>
    <Properties>
      <SchemaBasedProperties>
        <LABEL
          ResId="pqt.dss.rrf.model.vo.DssReinstatementRequestFormView.MgrAgentName_LABEL"/>
      </SchemaBasedProperties>
    </Properties>
  </ViewAttribute>
  <ViewAttribute
    Name="MgrNNo"
    IsPersistent="false"
    PrecisionRule="true"
    Type="oracle.jbo.domain.Number"
    ColumnType="NUMBER"
    AliasName="MGR_N_NO"
    Expression="MGR_N_NO"
    SQLType="NUMERIC"/>
  <ViewAttribute
    Name="MgrName"
    IsPersistent="false"
    PrecisionRule="true"
    Precision="4000"
    Type="java.lang.String"
    ColumnType="VARCHAR2"
    AliasName="MGR_NAME"
    Expression="MGR_NAME"
    SQLType="VARCHAR">
    <DesignTime>
      <Attr Name="_DisplaySize" Value="4000"/>
    </DesignTime>
    <Properties>
      <SchemaBasedProperties>
        <LABEL
          ResId="pqt.dss.rrf.model.vo.DssReinstatementRequestFormView.MgrName_LABEL"/>
        <DISPLAYWIDTH
          Value="50"/>
      </SchemaBasedProperties>
    </Properties>
  </ViewAttribute>
  <ViewAttribute
    Name="MgrCode"
    IsPersistent="false"
    PrecisionRule="true"
    Precision="4000"
    Type="java.lang.String"
    ColumnType="VARCHAR2"
    AliasName="MGR_CODE"
    Expression="MGR_CODE"
    SQLType="VARCHAR"
    LOVName="LOV_MgrCode">
    <DesignTime>
      <Attr Name="_DisplaySize" Value="4000"/>
    </DesignTime>
    <Properties>
      <SchemaBasedProperties>
        <LABEL
          ResId="pqt.dss.rrf.model.vo.DssReinstatementRequestFormView.MgrCode_LABEL"/>
        <DISPLAYWIDTH
          Value="50"/>
        <CONTROLTYPE
          Value="input_text_lov"/>
      </SchemaBasedProperties>
    </Properties>
  </ViewAttribute>
  <ViewAttribute
    Name="CurrentDesignation"
    IsPersistent="false"
    PrecisionRule="true"
    Precision="100"
    Type="java.lang.String"
    ColumnType="VARCHAR2"
    AliasName="CURRENT_DESIGNATION"
    Expression="CURRENT_DESIGNATION"
    SQLType="VARCHAR">
    <DesignTime>
      <Attr Name="_DisplaySize" Value="100"/>
    </DesignTime>
    <Properties>
      <SchemaBasedProperties>
        <DISPLAYWIDTH
          Value="50"/>
        <LABEL
          ResId="pqt.dss.rrf.model.vo.DssReinstatementRequestFormView.CurrentDesignation_LABEL"/>
      </SchemaBasedProperties>
    </Properties>
  </ViewAttribute>
  <ViewAttribute
    Name="Nlevel"
    IsPersistent="false"
    PrecisionRule="true"
    Type="java.lang.Long"
    ColumnType="NUMBER"
    AliasName="NLEVEL"
    Expression="NLEVEL"
    SQLType="NUMERIC"/>
  <ViewAttribute
    Name="CurrentBranch"
    IsPersistent="false"
    PrecisionRule="true"
    Precision="500"
    Type="java.lang.String"
    ColumnType="VARCHAR2"
    AliasName="CURRENT_BRANCH"
    Expression="CURRENT_BRANCH"
    SQLType="VARCHAR"
    LOVName="UsertBranchDtlLOV">
    <DesignTime>
      <Attr Name="_DisplaySize" Value="500"/>
    </DesignTime>
    <Properties>
      <SchemaBasedProperties>
        <DISPLAYWIDTH
          Value="50"/>
        <LABEL
          ResId="pqt.dss.rrf.model.vo.DssReinstatementRequestFormView.CurrentBranch_LABEL"/>
        <CONTROLTYPE
          Value="choice"/>
      </SchemaBasedProperties>
    </Properties>
  </ViewAttribute>
  <ViewAttribute
    Name="NewBranch"
    IsPersistent="false"
    PrecisionRule="true"
    Precision="500"
    Type="java.lang.String"
    ColumnType="VARCHAR2"
    AliasName="NEW_BRANCH"
    Expression="NEW_BRANCH"
    SQLType="VARCHAR"
    IsNotNull="true"
    LOVName="LOV_NewBranch">
    <DesignTime>
      <Attr Name="_DisplaySize" Value="500"/>
    </DesignTime>
    <Properties>
      <SchemaBasedProperties>
        <LABEL
          ResId="pqt.dss.rrf.model.vo.DssReinstatementRequestFormView.NewBranch_LABEL"/>
        <DISPLAYWIDTH
          Value="50"/>
        <CONTROLTYPE
          Value="input_text_lov"/>
      </SchemaBasedProperties>
    </Properties>
  </ViewAttribute>
  <ViewAttribute
    Name="UserBranch"
    IsUpdateable="false"
    IsPersistent="false"
    PrecisionRule="true"
    Precision="500"
    Type="java.lang.String"
    ColumnType="VARCHAR2"
    AliasName="USER_BRANCH"
    Expression="USER_BRANCH"
    SQLType="VARCHAR">
    <DesignTime>
      <Attr Name="_DisplaySize" Value="500"/>
    </DesignTime>
  </ViewAttribute>
  <ViewAttribute
    Name="NoOfTermination"
    IsPersistent="false"
    PrecisionRule="true"
    Type="oracle.jbo.domain.Number"
    ColumnType="NUMBER"
    AliasName="NO_OF_TERMINATION"
    Expression="NO_OF_TERMINATION"
    SQLType="NUMERIC">
    <Properties>
      <SchemaBasedProperties>
        <LABEL
          ResId="pqt.dss.rrf.model.vo.DssReinstatementRequestFormView.NoOfTermination_LABEL"/>
      </SchemaBasedProperties>
    </Properties>
  </ViewAttribute>
  <ViewAttribute
    Name="NoOfResignation"
    IsPersistent="false"
    PrecisionRule="true"
    Type="oracle.jbo.domain.Number"
    ColumnType="NUMBER"
    AliasName="NO_OF_RESIGNATION"
    Expression="NO_OF_RESIGNATION"
    SQLType="NUMERIC">
    <Properties>
      <SchemaBasedProperties>
        <LABEL
          ResId="pqt.dss.rrf.model.vo.DssReinstatementRequestFormView.NoOfResignation_LABEL"/>
      </SchemaBasedProperties>
    </Properties>
  </ViewAttribute>
  <ViewCriteria
    Name="DssReinstatementRequestFormViewCriteria"
    ViewObjectName="pqt.dss.rrf.model.vo.DssReinstatementRequestFormView"
    Conjunction="AND">
    <Properties Name="_Props">
      <CustomProperties>
        <Property
          Name="autoExecute"
          Value="false"/>
        <Property
          Name="mode"
          Value="Basic"/>
        <Property
          Name="allowConjunctionOverride"
          Value="true"/>
        <Property
          Name="showInList"
          Value="true"/>
        <Property
          Name="displayOperators"
          Value="InAdvancedMode"/>
      </CustomProperties>
    </Properties>
    <ViewCriteriaRow
      Name="DssReinstatementRequestFormViewCriteria_row_0"
      UpperColumns="1">
      <ViewCriteriaItem
        Name="BankAccNo"
        ViewAttribute="BankAccNo"
        Operator="CONTAINS"
        Conjunction="AND"
        Value=":VC_ACCOUNT_NO"
        IsBindVarValue="true"
        Required="Optional"/>
      <ViewCriteriaItem
        Name="RrfDocNo"
        ViewAttribute="RrfDocNo"
        Operator="CONTAINS"
        Conjunction="AND"
        Value=":VC_Doc_No"
        IsBindVarValue="true"
        Required="Optional"/>
      <ViewCriteriaItem
        Name="MgrAgentName"
        ViewAttribute="MgrAgentName"
        Operator="CONTAINS"
        Conjunction="AND"
        Value=":VC_Manager_Agent_Name"
        IsBindVarValue="true"
        Required="Optional"/>
    </ViewCriteriaRow>
  </ViewCriteria>
  <ViewCriteria
    Name="NotificationViewCriteria"
    ViewObjectName="pqt.dss.rrf.model.vo.DssReinstatementRequestFormView"
    Conjunction="AND">
    <Properties Name="_Props">
      <CustomProperties>
        <Property
          Name="autoExecute"
          Value="false"/>
        <Property
          Name="mode"
          Value="Basic"/>
        <Property
          Name="allowConjunctionOverride"
          Value="true"/>
        <Property
          Name="showInList"
          Value="true"/>
        <Property
          Name="displayOperators"
          Value="InAdvancedMode"/>
      </CustomProperties>
    </Properties>
    <ViewCriteriaRow
      Name="DssReinstatementRequestFormViewCriteria1_row_0"
      UpperColumns="1">
      <ViewCriteriaItem
        Name="RrfIdPk"
        ViewAttribute="RrfIdPk"
        Operator="="
        Conjunction="AND"
        Value=":NVC_WfDocumentId"
        IsBindVarValue="true"
        Required="Optional"/>
    </ViewCriteriaRow>
  </ViewCriteria>
  <ViewLinkAccessor
    Name="DssReinstatementExistMgrView"
    ViewLink="pqt.dss.rrf.model.vl.DssHeadToMgr"
    Type="oracle.jbo.RowIterator"
    IsUpdateable="false"/>
  <ViewLinkAccessor
    Name="DssReinstatementNewHiringView"
    ViewLink="pqt.dss.rrf.model.vl.RfrtNewFkVL"
    Type="oracle.jbo.RowIterator"
    IsUpdateable="false"/>
  <ClientInterface
    Name="__clientInterface">
    <Method
      Name="setNVC_WfDocumentId"
      MethodName="setNVC_WfDocumentId">
      <Return
        Name="_return_type_"
        Type="void"/>
      <Parameter
        Name="value"
        Type="oracle.jbo.domain.Number"/>
    </Method>
    <Method
      Name="setNVC_WfDocumentId"
      MethodName="setNVC_WfDocumentId">
      <Return
        Name="_return_type_"
        Type="void"/>
      <Parameter
        Name="value"
        Type="oracle.jbo.domain.Number"/>
    </Method>
    <Method
      Name="setNVC_WfDocumentId"
      MethodName="setNVC_WfDocumentId">
      <Return
        Name="_return_type_"
        Type="void"/>
      <Parameter
        Name="value"
        Type="oracle.jbo.domain.Number"/>
    </Method>
    <Method
      Name="setNVC_WfDocumentId"
      MethodName="setNVC_WfDocumentId">
      <Return
        Name="_return_type_"
        Type="void"/>
      <Parameter
        Name="value"
        Type="oracle.jbo.domain.Number"/>
    </Method>
    <Method
      Name="rrfSearchUser"
      MethodName="rrfSearchUser">
      <Return
        Name="_return_type_"
        Type="void"/>
    </Method>
  </ClientInterface>
  <ResourceBundle>
    <PropertiesBundle
      PropertiesFile="pqt.dss.rrf.model.RRFModelBundle"/>
  </ResourceBundle>
</ViewObject>
